typsync/__init__.py
typsync/cli.py
typsync/py.typed
typsync-0.0.1.dist-info/METADATA
typsync-0.0.1.dist-info/WHEEL
typsync-0.0.1.dist-info/entry_points.txt
typsync-0.0.1.dist-info/licenses/LICENSE
typsync-0.0.1.dist-info/RECORD
