Metadata-Version: 2.4
Name: typsync
Version: 0.0.1
Project-URL: Documentation, https://daizutabi.github.io/typsync/
Project-URL: Source, https://github.com/daizutabi/typsync
Project-URL: Issues, https://github.com/daizutabi/typsync/issues
Author-email: daizutabi <daizutabi@gmail.com>
License: MIT License
License-File: LICENSE
Keywords: academic,document,jupyter,notebook,pdf,publication,research,scientific,visualization
Classifier: Development Status :: 4 - Beta
Classifier: Intended Audience :: Education
Classifier: Intended Audience :: Science/Research
Classifier: License :: OSI Approved :: MIT License
Classifier: Operating System :: OS Independent
Classifier: Programming Language :: Python
Classifier: Programming Language :: Python :: 3.10
Classifier: Programming Language :: Python :: 3.11
Classifier: Programming Language :: Python :: 3.12
Classifier: Programming Language :: Python :: 3.13
Classifier: Topic :: Documentation
Classifier: Topic :: Scientific/Engineering
Classifier: Topic :: Software Development :: Documentation
Classifier: Topic :: Text Processing :: Markup
Requires-Python: >=3.10
Requires-Dist: aiohttp>=3
Requires-Dist: nbstore>=0.4.1
Requires-Dist: pyzotero>=1.6
Requires-Dist: rich>=13
Requires-Dist: typer>=0.15
Requires-Dist: watchfiles>=1
